.DS_Store
airspeed/__init__.py
airspeed/api.py
airspeed-0.6.1.dist-info/LICENCE
airspeed-0.6.1.dist-info/METADATA
airspeed-0.6.1.dist-info/WHEEL
airspeed-0.6.1.dist-info/top_level.txt
airspeed-0.6.1.dist-info/RECORD
