Metadata-Version: 2.1
Name: airspeed
Version: 0.6.1
Summary: Airspeed is a powerful and easy-to-use templating engine for Python that aims for a high level of compatibility with the popular Velocity library for Java.
Home-page: https://github.com/purcell/airspeed
Author: Steve Purcell and Chris Tarttelin
Author-email: steve@pythonconsulting.com, chris@pythonconsulting.com
License: BSD
Classifier: Environment :: Web Environment
Classifier: Intended Audience :: Developers
Classifier: License :: OSI Approved :: BSD License
Classifier: Operating System :: OS Independent
Classifier: Programming Language :: Python
Classifier: Topic :: Internet :: WWW/HTTP :: Dynamic Content
Classifier: Topic :: Software Development :: Libraries :: Python Modules
Classifier: Programming Language :: Python :: 3.9
Classifier: Programming Language :: Python :: 3.10
Classifier: Programming Language :: Python :: 3.11
Classifier: Programming Language :: Python :: 3.12
Classifier: Programming Language :: Python :: 3.13
License-File: LICENCE
Requires-Dist: six
Requires-Dist: cachetools
